murray/__init__.py
murray/layout.html
murray/theme.conf
murray/murray/layout.html
murray/murray/theme.conf
murray/murray/static/favicon.ico
murray/murray/static/css/main.css
murray/murray/static/css/normalize.css
murray/murray/static/css/normalize.min.css
murray/murray/static/js/main.js
murray/murray/static/js/vendor/modernizr-2.8.3-respond-1.4.2.min.js
murray/static/favicon.ico
murray/static/css/main.css
murray/static/css/normalize.css
murray/static/css/normalize.min.css
murray/static/img/flourish.svg
murray/static/js/main.js
murray/static/js/vendor/modernizr-2.8.3-respond-1.4.2.min.js
murray-0.6.4.dist-info/DESCRIPTION.rst
murray-0.6.4.dist-info/METADATA
murray-0.6.4.dist-info/RECORD
murray-0.6.4.dist-info/WHEEL
murray-0.6.4.dist-info/entry_points.txt
murray-0.6.4.dist-info/metadata.json
murray-0.6.4.dist-info/top_level.txt
